CHANGELOG
COPYRIGHT
INSTALL
LICENSE
MANIFEST.in
README
setup.py
antbkp/__init__.py
antbkp/home.py
antbkp/mysql.py
antbkp/psql.py
antbkp/rotate.py
antbkp/version.py
antbkp.egg-info/PKG-INFO
antbkp.egg-info/SOURCES.txt
antbkp.egg-info/dependency_links.txt
antbkp.egg-info/top_level.txt
bin/antbkp
etc/antbkp.cfg