Metadata-Version: 1.1
Name: antbkp
Version: 0.0.1
Summary: Ant Backup. Simple Backup: Files, Rotation backups, Postgres, Mysql, OpenERP, Tryton,...
Home-page: https://www.zikzakmedia.com
Author: Zikzakmedia SL
Author-email: zikzak@zikzakmedia.com
License: GPL-3
Download-URL: https://bitbucket.org/zikzakmedia/python-antbkp
Platform: UNKNOWN
Classifier: Development Status :: 4 - Beta
Classifier: Environment :: Web Environment
Classifier: Intended Audience :: Developers
Classifier: License :: OSI Approved :: GNU Affero General Public License v3
Classifier: Operating System :: OS Independent
Classifier: Programming Language :: Python
Classifier: Topic :: Internet :: WWW/HTTP :: Dynamic Content
Classifier: Topic :: Software Development :: Libraries :: Python Modules
